negotium/__init__.py
negotium/base.py
negotium/conf.py
negotium/task.py
negotium/brokers/__init__.py
negotium/brokers/main.py
negotium/brokers/redis.py
negotium/mq/__init__.py
negotium/mq/consumer.py
negotium/mq/publisher.py
negotium/mq/trackers.py
negotium/schedules/__init__.py
negotium/schedules/crontab.py
negotium/utils/__init__.py
negotium/utils/logger.py
negotium-0.2.6.dist-info/LICENSE
negotium-0.2.6.dist-info/METADATA
negotium-0.2.6.dist-info/WHEEL
negotium-0.2.6.dist-info/top_level.txt
negotium-0.2.6.dist-info/RECORD
