Metadata-Version: 2.1
Name: negotium
Version: 0.2.6
Summary: A lightweight and easy to use task queue/scheduler
Requires-Python: >=3.7
License-File: LICENSE
Requires-Dist: async-timeout ==4.0.2
Requires-Dist: redis ==4.5.4
Requires-Dist: sortedcontainers ==2.4.0
Requires-Dist: typeguard ==3.0.2
Requires-Dist: typing-extensions >=4.5.0
Requires-Dist: croniter ==1.3.14
